<?xml version="1.0" encoding="UTF-8"?>
<DEFECTS>
  <DEFECT>
    <SFA>
      <FILEPATH>c:\users\joka8837\onedrive\c++ projects\thenextfrontier\thenextfrontier\thenextfrontier\</FILEPATH>
      <FILENAME>cameraclass.cpp</FILENAME>
      <LINE>3</LINE>
      <COLUMN>13</COLUMN>
    </SFA>
    <DEFECTCODE>26495</DEFECTCODE>
    <DESCRIPTION>Variable 'CameraClass::mViewMatrix' is uninitialized. Always initialize a member variable (type.6).</DESCRIPTION>
    <FUNCTION>CameraClass::{ctor}</FUNCTION>
    <DECORATED>??0CameraClass@@QEAA@XZ</DECORATED>
    <FUNCLINE>3</FUNCLINE>
    <PATH></PATH>
  </DEFECT>
  <DEFECT>
    <SFA>
      <FILEPATH>c:\users\joka8837\onedrive\c++ projects\thenextfrontier\thenextfrontier\thenextfrontier\</FILEPATH>
      <FILENAME>cameraclass.cpp</FILENAME>
      <LINE>3</LINE>
      <COLUMN>13</COLUMN>
    </SFA>
    <DEFECTCODE>26495</DEFECTCODE>
    <DESCRIPTION>Variable 'CameraClass::mBaseViewMatrix' is uninitialized. Always initialize a member variable (type.6).</DESCRIPTION>
    <FUNCTION>CameraClass::{ctor}</FUNCTION>
    <DECORATED>??0CameraClass@@QEAA@XZ</DECORATED>
    <FUNCLINE>3</FUNCLINE>
    <PATH></PATH>
  </DEFECT>
  <DEFECT>
    <SFA>
      <FILEPATH>c:\users\joka8837\onedrive\c++ projects\thenextfrontier\thenextfrontier\thenextfrontier\</FILEPATH>
      <FILENAME>cameraclass.cpp</FILENAME>
      <LINE>3</LINE>
      <COLUMN>13</COLUMN>
    </SFA>
    <DEFECTCODE>26495</DEFECTCODE>
    <DESCRIPTION>Variable 'CameraClass::mLookAt' is uninitialized. Always initialize a member variable (type.6).</DESCRIPTION>
    <FUNCTION>CameraClass::{ctor}</FUNCTION>
    <DECORATED>??0CameraClass@@QEAA@XZ</DECORATED>
    <FUNCLINE>3</FUNCLINE>
    <PATH></PATH>
  </DEFECT>
  <DEFECT>
    <SFA>
      <FILEPATH>c:\users\joka8837\onedrive\c++ projects\thenextfrontier\thenextfrontier\thenextfrontier\</FILEPATH>
      <FILENAME>cameraclass.cpp</FILENAME>
      <LINE>3</LINE>
      <COLUMN>13</COLUMN>
    </SFA>
    <DEFECTCODE>26495</DEFECTCODE>
    <DESCRIPTION>Variable 'CameraClass::mUp' is uninitialized. Always initialize a member variable (type.6).</DESCRIPTION>
    <FUNCTION>CameraClass::{ctor}</FUNCTION>
    <DECORATED>??0CameraClass@@QEAA@XZ</DECORATED>
    <FUNCLINE>3</FUNCLINE>
    <PATH></PATH>
  </DEFECT>
  <DEFECT>
    <SFA>
      <FILEPATH>c:\users\joka8837\onedrive\c++ projects\thenextfrontier\thenextfrontier\thenextfrontier\</FILEPATH>
      <FILENAME>cameraclass.cpp</FILENAME>
      <LINE>3</LINE>
      <COLUMN>13</COLUMN>
    </SFA>
    <DEFECTCODE>26495</DEFECTCODE>
    <DESCRIPTION>Variable 'CameraClass::mFOV' is uninitialized. Always initialize a member variable (type.6).</DESCRIPTION>
    <FUNCTION>CameraClass::{ctor}</FUNCTION>
    <DECORATED>??0CameraClass@@QEAA@XZ</DECORATED>
    <FUNCLINE>3</FUNCLINE>
    <PATH></PATH>
  </DEFECT>
  <DEFECT>
    <SFA>
      <FILEPATH>c:\users\joka8837\onedrive\c++ projects\thenextfrontier\thenextfrontier\thenextfrontier\</FILEPATH>
      <FILENAME>cameraclass.cpp</FILENAME>
      <LINE>3</LINE>
      <COLUMN>13</COLUMN>
    </SFA>
    <DEFECTCODE>26439</DEFECTCODE>
    <DESCRIPTION>This kind of function may not throw. Declare it 'noexcept' (f.6).</DESCRIPTION>
    <FUNCTION>CameraClass::{ctor}</FUNCTION>
    <DECORATED>??0CameraClass@@QEAA@XZ</DECORATED>
    <FUNCLINE>3</FUNCLINE>
    <PATH></PATH>
  </DEFECT>
  <DEFECT>
    <SFA>
      <FILEPATH>c:\users\joka8837\onedrive\c++ projects\thenextfrontier\thenextfrontier\thenextfrontier\</FILEPATH>
      <FILENAME>cameraclass.cpp</FILENAME>
      <LINE>22</LINE>
      <COLUMN>13</COLUMN>
    </SFA>
    <DEFECTCODE>26495</DEFECTCODE>
    <DESCRIPTION>Variable 'CameraClass::mViewMatrix' is uninitialized. Always initialize a member variable (type.6).</DESCRIPTION>
    <FUNCTION>CameraClass::{ctor}</FUNCTION>
    <DECORATED>??0CameraClass@@QEAA@AEBV0@@Z</DECORATED>
    <FUNCLINE>22</FUNCLINE>
    <PATH></PATH>
  </DEFECT>
  <DEFECT>
    <SFA>
      <FILEPATH>c:\users\joka8837\onedrive\c++ projects\thenextfrontier\thenextfrontier\thenextfrontier\</FILEPATH>
      <FILENAME>cameraclass.cpp</FILENAME>
      <LINE>22</LINE>
      <COLUMN>13</COLUMN>
    </SFA>
    <DEFECTCODE>26495</DEFECTCODE>
    <DESCRIPTION>Variable 'CameraClass::mBaseViewMatrix' is uninitialized. Always initialize a member variable (type.6).</DESCRIPTION>
    <FUNCTION>CameraClass::{ctor}</FUNCTION>
    <DECORATED>??0CameraClass@@QEAA@AEBV0@@Z</DECORATED>
    <FUNCLINE>22</FUNCLINE>
    <PATH></PATH>
  </DEFECT>
  <DEFECT>
    <SFA>
      <FILEPATH>c:\users\joka8837\onedrive\c++ projects\thenextfrontier\thenextfrontier\thenextfrontier\</FILEPATH>
      <FILENAME>cameraclass.cpp</FILENAME>
      <LINE>22</LINE>
      <COLUMN>13</COLUMN>
    </SFA>
    <DEFECTCODE>26495</DEFECTCODE>
    <DESCRIPTION>Variable 'CameraClass::mLookAt' is uninitialized. Always initialize a member variable (type.6).</DESCRIPTION>
    <FUNCTION>CameraClass::{ctor}</FUNCTION>
    <DECORATED>??0CameraClass@@QEAA@AEBV0@@Z</DECORATED>
    <FUNCLINE>22</FUNCLINE>
    <PATH></PATH>
  </DEFECT>
  <DEFECT>
    <SFA>
      <FILEPATH>c:\users\joka8837\onedrive\c++ projects\thenextfrontier\thenextfrontier\thenextfrontier\</FILEPATH>
      <FILENAME>cameraclass.cpp</FILENAME>
      <LINE>22</LINE>
      <COLUMN>13</COLUMN>
    </SFA>
    <DEFECTCODE>26495</DEFECTCODE>
    <DESCRIPTION>Variable 'CameraClass::mUp' is uninitialized. Always initialize a member variable (type.6).</DESCRIPTION>
    <FUNCTION>CameraClass::{ctor}</FUNCTION>
    <DECORATED>??0CameraClass@@QEAA@AEBV0@@Z</DECORATED>
    <FUNCLINE>22</FUNCLINE>
    <PATH></PATH>
  </DEFECT>
  <DEFECT>
    <SFA>
      <FILEPATH>c:\users\joka8837\onedrive\c++ projects\thenextfrontier\thenextfrontier\thenextfrontier\</FILEPATH>
      <FILENAME>cameraclass.cpp</FILENAME>
      <LINE>22</LINE>
      <COLUMN>13</COLUMN>
    </SFA>
    <DEFECTCODE>26495</DEFECTCODE>
    <DESCRIPTION>Variable 'CameraClass::mFOV' is uninitialized. Always initialize a member variable (type.6).</DESCRIPTION>
    <FUNCTION>CameraClass::{ctor}</FUNCTION>
    <DECORATED>??0CameraClass@@QEAA@AEBV0@@Z</DECORATED>
    <FUNCLINE>22</FUNCLINE>
    <PATH></PATH>
  </DEFECT>
  <DEFECT>
    <SFA>
      <FILEPATH>c:\users\joka8837\onedrive\c++ projects\thenextfrontier\thenextfrontier\thenextfrontier\</FILEPATH>
      <FILENAME>cameraclass.cpp</FILENAME>
      <LINE>22</LINE>
      <COLUMN>13</COLUMN>
    </SFA>
    <DEFECTCODE>26495</DEFECTCODE>
    <DESCRIPTION>Variable 'CameraClass::mOldRotationZ' is uninitialized. Always initialize a member variable (type.6).</DESCRIPTION>
    <FUNCTION>CameraClass::{ctor}</FUNCTION>
    <DECORATED>??0CameraClass@@QEAA@AEBV0@@Z</DECORATED>
    <FUNCLINE>22</FUNCLINE>
    <PATH></PATH>
  </DEFECT>
  <DEFECT>
    <SFA>
      <FILEPATH>c:\users\joka8837\onedrive\c++ projects\thenextfrontier\thenextfrontier\thenextfrontier\</FILEPATH>
      <FILENAME>cameraclass.cpp</FILENAME>
      <LINE>22</LINE>
      <COLUMN>13</COLUMN>
    </SFA>
    <DEFECTCODE>26495</DEFECTCODE>
    <DESCRIPTION>Variable 'CameraClass::mOldRotationY' is uninitialized. Always initialize a member variable (type.6).</DESCRIPTION>
    <FUNCTION>CameraClass::{ctor}</FUNCTION>
    <DECORATED>??0CameraClass@@QEAA@AEBV0@@Z</DECORATED>
    <FUNCLINE>22</FUNCLINE>
    <PATH></PATH>
  </DEFECT>
  <DEFECT>
    <SFA>
      <FILEPATH>c:\users\joka8837\onedrive\c++ projects\thenextfrontier\thenextfrontier\thenextfrontier\</FILEPATH>
      <FILENAME>cameraclass.cpp</FILENAME>
      <LINE>22</LINE>
      <COLUMN>13</COLUMN>
    </SFA>
    <DEFECTCODE>26495</DEFECTCODE>
    <DESCRIPTION>Variable 'CameraClass::mOldRotationX' is uninitialized. Always initialize a member variable (type.6).</DESCRIPTION>
    <FUNCTION>CameraClass::{ctor}</FUNCTION>
    <DECORATED>??0CameraClass@@QEAA@AEBV0@@Z</DECORATED>
    <FUNCLINE>22</FUNCLINE>
    <PATH></PATH>
  </DEFECT>
  <DEFECT>
    <SFA>
      <FILEPATH>c:\users\joka8837\onedrive\c++ projects\thenextfrontier\thenextfrontier\thenextfrontier\</FILEPATH>
      <FILENAME>cameraclass.cpp</FILENAME>
      <LINE>22</LINE>
      <COLUMN>13</COLUMN>
    </SFA>
    <DEFECTCODE>26495</DEFECTCODE>
    <DESCRIPTION>Variable 'CameraClass::mOldPositionZ' is uninitialized. Always initialize a member variable (type.6).</DESCRIPTION>
    <FUNCTION>CameraClass::{ctor}</FUNCTION>
    <DECORATED>??0CameraClass@@QEAA@AEBV0@@Z</DECORATED>
    <FUNCLINE>22</FUNCLINE>
    <PATH></PATH>
  </DEFECT>
  <DEFECT>
    <SFA>
      <FILEPATH>c:\users\joka8837\onedrive\c++ projects\thenextfrontier\thenextfrontier\thenextfrontier\</FILEPATH>
      <FILENAME>cameraclass.cpp</FILENAME>
      <LINE>22</LINE>
      <COLUMN>13</COLUMN>
    </SFA>
    <DEFECTCODE>26495</DEFECTCODE>
    <DESCRIPTION>Variable 'CameraClass::mOldPositionX' is uninitialized. Always initialize a member variable (type.6).</DESCRIPTION>
    <FUNCTION>CameraClass::{ctor}</FUNCTION>
    <DECORATED>??0CameraClass@@QEAA@AEBV0@@Z</DECORATED>
    <FUNCLINE>22</FUNCLINE>
    <PATH></PATH>
  </DEFECT>
  <DEFECT>
    <SFA>
      <FILEPATH>c:\users\joka8837\onedrive\c++ projects\thenextfrontier\thenextfrontier\thenextfrontier\</FILEPATH>
      <FILENAME>cameraclass.cpp</FILENAME>
      <LINE>22</LINE>
      <COLUMN>13</COLUMN>
    </SFA>
    <DEFECTCODE>26495</DEFECTCODE>
    <DESCRIPTION>Variable 'CameraClass::mOldPositionY' is uninitialized. Always initialize a member variable (type.6).</DESCRIPTION>
    <FUNCTION>CameraClass::{ctor}</FUNCTION>
    <DECORATED>??0CameraClass@@QEAA@AEBV0@@Z</DECORATED>
    <FUNCLINE>22</FUNCLINE>
    <PATH></PATH>
  </DEFECT>
  <DEFECT>
    <SFA>
      <FILEPATH>c:\users\joka8837\onedrive\c++ projects\thenextfrontier\thenextfrontier\thenextfrontier\</FILEPATH>
      <FILENAME>cameraclass.cpp</FILENAME>
      <LINE>22</LINE>
      <COLUMN>13</COLUMN>
    </SFA>
    <DEFECTCODE>26495</DEFECTCODE>
    <DESCRIPTION>Variable 'CameraClass::mPositionZ' is uninitialized. Always initialize a member variable (type.6).</DESCRIPTION>
    <FUNCTION>CameraClass::{ctor}</FUNCTION>
    <DECORATED>??0CameraClass@@QEAA@AEBV0@@Z</DECORATED>
    <FUNCLINE>22</FUNCLINE>
    <PATH></PATH>
  </DEFECT>
  <DEFECT>
    <SFA>
      <FILEPATH>c:\users\joka8837\onedrive\c++ projects\thenextfrontier\thenextfrontier\thenextfrontier\</FILEPATH>
      <FILENAME>cameraclass.cpp</FILENAME>
      <LINE>22</LINE>
      <COLUMN>13</COLUMN>
    </SFA>
    <DEFECTCODE>26495</DEFECTCODE>
    <DESCRIPTION>Variable 'CameraClass::mRotationZ' is uninitialized. Always initialize a member variable (type.6).</DESCRIPTION>
    <FUNCTION>CameraClass::{ctor}</FUNCTION>
    <DECORATED>??0CameraClass@@QEAA@AEBV0@@Z</DECORATED>
    <FUNCLINE>22</FUNCLINE>
    <PATH></PATH>
  </DEFECT>
  <DEFECT>
    <SFA>
      <FILEPATH>c:\users\joka8837\onedrive\c++ projects\thenextfrontier\thenextfrontier\thenextfrontier\</FILEPATH>
      <FILENAME>cameraclass.cpp</FILENAME>
      <LINE>22</LINE>
      <COLUMN>13</COLUMN>
    </SFA>
    <DEFECTCODE>26495</DEFECTCODE>
    <DESCRIPTION>Variable 'CameraClass::mPositionY' is uninitialized. Always initialize a member variable (type.6).</DESCRIPTION>
    <FUNCTION>CameraClass::{ctor}</FUNCTION>
    <DECORATED>??0CameraClass@@QEAA@AEBV0@@Z</DECORATED>
    <FUNCLINE>22</FUNCLINE>
    <PATH></PATH>
  </DEFECT>
  <DEFECT>
    <SFA>
      <FILEPATH>c:\users\joka8837\onedrive\c++ projects\thenextfrontier\thenextfrontier\thenextfrontier\</FILEPATH>
      <FILENAME>cameraclass.cpp</FILENAME>
      <LINE>22</LINE>
      <COLUMN>13</COLUMN>
    </SFA>
    <DEFECTCODE>26495</DEFECTCODE>
    <DESCRIPTION>Variable 'CameraClass::mRotationX' is uninitialized. Always initialize a member variable (type.6).</DESCRIPTION>
    <FUNCTION>CameraClass::{ctor}</FUNCTION>
    <DECORATED>??0CameraClass@@QEAA@AEBV0@@Z</DECORATED>
    <FUNCLINE>22</FUNCLINE>
    <PATH></PATH>
  </DEFECT>
  <DEFECT>
    <SFA>
      <FILEPATH>c:\users\joka8837\onedrive\c++ projects\thenextfrontier\thenextfrontier\thenextfrontier\</FILEPATH>
      <FILENAME>cameraclass.cpp</FILENAME>
      <LINE>22</LINE>
      <COLUMN>13</COLUMN>
    </SFA>
    <DEFECTCODE>26495</DEFECTCODE>
    <DESCRIPTION>Variable 'CameraClass::mRotationY' is uninitialized. Always initialize a member variable (type.6).</DESCRIPTION>
    <FUNCTION>CameraClass::{ctor}</FUNCTION>
    <DECORATED>??0CameraClass@@QEAA@AEBV0@@Z</DECORATED>
    <FUNCLINE>22</FUNCLINE>
    <PATH></PATH>
  </DEFECT>
  <DEFECT>
    <SFA>
      <FILEPATH>c:\users\joka8837\onedrive\c++ projects\thenextfrontier\thenextfrontier\thenextfrontier\</FILEPATH>
      <FILENAME>cameraclass.cpp</FILENAME>
      <LINE>22</LINE>
      <COLUMN>13</COLUMN>
    </SFA>
    <DEFECTCODE>26495</DEFECTCODE>
    <DESCRIPTION>Variable 'CameraClass::mPositionX' is uninitialized. Always initialize a member variable (type.6).</DESCRIPTION>
    <FUNCTION>CameraClass::{ctor}</FUNCTION>
    <DECORATED>??0CameraClass@@QEAA@AEBV0@@Z</DECORATED>
    <FUNCLINE>22</FUNCLINE>
    <PATH></PATH>
  </DEFECT>
</DEFECTS>